TDistributionClassifier/TDistributionClassifier.py
TDistributionClassifier/__init__.py
TDistributionClassifier-1.2.0.dist-info/LICENSE
TDistributionClassifier-1.2.0.dist-info/METADATA
TDistributionClassifier-1.2.0.dist-info/WHEEL
TDistributionClassifier-1.2.0.dist-info/top_level.txt
TDistributionClassifier-1.2.0.dist-info/RECORD
