Metadata-Version: 2.2
Name: TDistributionClassifier
Version: 1.2.0
Summary: A binary classifier using Student's t-distribution for univariate and multivariate continuous data.
Home-page: https://github.com/Luckyy0311
Author: Abdul Mofique Siddiqui
Author-email: mofique7860@gmail.com
License: MIT
Classifier: Development Status :: 4 - Beta
Classifier: Intended Audience :: Science/Research
Classifier: License :: OSI Approved :: MIT License
Classifier: Programming Language :: Python :: 3
Classifier: Topic :: Scientific/Engineering :: Artificial Intelligence
Requires-Python: >=3.6
License-File: LICENSE
Requires-Dist: numpy
Requires-Dist: scipy
Dynamic: author
Dynamic: author-email
Dynamic: classifier
Dynamic: description
Dynamic: description-content-type
Dynamic: home-page
Dynamic: license
Dynamic: requires-dist
Dynamic: requires-python
Dynamic: summary
